{
  "button": {
    "primary": {
      "background": {
        "value": "{accent.default}",
        "type": "color",
        "failedToResolve": true
      },
      "text": {
        "value": "{accent.onAccent}",
        "type": "color",
        "failedToResolve": true
      }
    },
    "borderRadius": {
      "value": "{borderRadius.lg}",
      "type": "borderRadius",
      "failedToResolve": true
    },
    "borderWidth": {
      "value": "{dimension.sm}",
      "type": "borderWidth",
      "failedToResolve": true
    }
  },
  "card": {
    "borderRadius": {
      "value": "{borderRadius.lg}",
      "type": "borderRadius",
      "failedToResolve": true
    },
    "background": {
      "value": "{bg.default}",
      "type": "color",
      "failedToResolve": true
    },
    "padding": {
      "value": "{dimension.md}",
      "type": "dimension",
      "failedToResolve": true
    }
  },
  "boxShadow": {
    "default": {
      "value": [
        {
          "x": 5,
          "y": 5,
          "spread": 3,
          "color": "rgba({shadows.default}, 0.15)",
          "blur": 5,
          "type": "dropShadow"
        },
        {
          "x": 4,
          "y": 4,
          "spread": 6,
          "color": "#00000033",
          "blur": 5,
          "type": "innerShadow"
        }
      ],
      "type": "boxShadow",
      "failedToResolve": true
    }
  },
  "typography": {
    "H1": {
      "Bold": {
        "type": "typography",
        "value": {
          "fontFamily": "{fontFamilies.heading}",
          "fontWeight": "{fontWeights.headingBold}",
          "lineHeight": "{lineHeights.heading}",
          "fontSize": "{fontSizes.h1}",
          "paragraphSpacing": "{paragraphSpacing.h1}",
          "letterSpacing": "{letterSpacing.decreased}"
        },
        "failedToResolve": true
      },
      "Regular": {
        "type": "typography",
        "value": {
          "fontFamily": "{fontFamilies.heading}",
          "fontWeight": "{fontWeights.headingRegular}",
          "lineHeight": "{lineHeights.heading}",
          "fontSize": "{fontSizes.h1}",
          "paragraphSpacing": "{paragraphSpacing.h1}",
          "letterSpacing": "{letterSpacing.decreased}"
        },
        "failedToResolve": true
      }
    },
    "H2": {
      "Bold": {
        "type": "typography",
        "value": {
          "fontFamily": "{fontFamilies.heading}",
          "fontWeight": "{fontWeights.headingBold}",
          "lineHeight": "{lineHeights.heading}",
          "fontSize": "{fontSizes.h2}",
          "paragraphSpacing": "{paragraphSpacing.h2}",
          "letterSpacing": "{letterSpacing.decreased}"
        },
        "failedToResolve": true
      },
      "Regular": {
        "type": "typography",
        "value": {
          "fontFamily": "{fontFamilies.heading}",
          "fontWeight": "{fontWeights.headingRegular}",
          "lineHeight": "{lineHeights.heading}",
          "fontSize": "{fontSizes.h2}",
          "paragraphSpacing": "{paragraphSpacing.h2}",
          "letterSpacing": "{letterSpacing.decreased}"
        },
        "failedToResolve": true
      }
    },
    "Body": {
      "type": "typography",
      "value": {
        "fontFamily": "{fontFamilies.body}",
        "fontWeight": "{fontWeights.bodyRegular}",
        "lineHeight": "{lineHeights.heading}",
        "fontSize": "{fontSizes.body}",
        "paragraphSpacing": "{paragraphSpacing.h2}"
      },
      "failedToResolve": true
    }
  },
  "Colors": {
    "black": {
      "value": "#121212",
      "type": "color"
    },
    "white": {
      "value": "#ffffff",
      "type": "color"
    },
    "brand": {
      "primary": {
        "light": {
          "value": "#9f7aea",
          "type": "color"
        },
        "dark": {
          "value": "#a787e8",
          "type": "color"
        }
      },
      "secondary": {
        "light": {
          "value": "#b794f4",
          "type": "color"
        },
        "dark": {
          "value": "#b898f1",
          "type": "color"
        }
      },
      "tertiary": {
        "light": {
          "value": "#d6bcfa",
          "type": "color"
        },
        "dark": {
          "value": "#d7bef8",
          "type": "color"
        }
      },
      "background": {
        "light": {
          "value": "#faf5ff",
          "type": "color"
        },
        "dark": {
          "value": "#faf5ff",
          "type": "color"
        }
      }
    },
    "gray": {
      "50": {
        "light": {
          "value": "#f7fafc",
          "type": "color"
        },
        "dark": {
          "value": "#171923",
          "type": "color"
        }
      },
      "100": {
        "light": {
          "value": "#edf2f7",
          "type": "color"
        },
        "dark": {
          "value": "#1a202c",
          "type": "color"
        }
      },
      "200": {
        "light": {
          "value": "#e2e8f0",
          "type": "color"
        },
        "dark": {
          "value": "#2d3748",
          "type": "color"
        }
      },
      "300": {
        "light": {
          "value": "#cbd5e0",
          "type": "color"
        },
        "dark": {
          "value": "#4a5568",
          "type": "color"
        }
      },
      "400": {
        "light": {
          "value": "#a0aec0",
          "type": "color"
        },
        "dark": {
          "value": "#718096",
          "type": "color"
        }
      },
      "500": {
        "light": {
          "value": "#718096",
          "type": "color"
        },
        "dark": {
          "value": "#a0aec0",
          "type": "color"
        }
      },
      "600": {
        "light": {
          "value": "#4a5568",
          "type": "color"
        },
        "dark": {
          "value": "#cbd5e0",
          "type": "color"
        }
      },
      "700": {
        "light": {
          "value": "#2d3748",
          "type": "color"
        },
        "dark": {
          "value": "#e2e8f0",
          "type": "color"
        }
      },
      "800": {
        "light": {
          "value": "#1a202c",
          "type": "color"
        },
        "dark": {
          "value": "#edf2f7",
          "type": "color"
        }
      },
      "900": {
        "light": {
          "value": "#171923",
          "type": "color"
        },
        "dark": {
          "value": "#f7fafc",
          "type": "color"
        }
      }
    },
    "opacity-white": {
      "50": {
        "light": {
          "value": "#ffffff0a",
          "type": "color"
        },
        "dark": {
          "value": "#0000000a",
          "type": "color"
        }
      },
      "100": {
        "light": {
          "value": "#ffffff0f",
          "type": "color"
        },
        "dark": {
          "value": "#0000000f",
          "type": "color"
        }
      },
      "200": {
        "light": {
          "value": "#ffffff14",
          "type": "color"
        },
        "dark": {
          "value": "#00000014",
          "type": "color"
        }
      },
      "300": {
        "light": {
          "value": "#ffffff29",
          "type": "color"
        },
        "dark": {
          "value": "#00000029",
          "type": "color"
        }
      },
      "400": {
        "light": {
          "value": "#ffffff3d",
          "type": "color"
        },
        "dark": {
          "value": "#0000003d",
          "type": "color"
        }
      },
      "500": {
        "light": {
          "value": "#ffffff5c",
          "type": "color"
        },
        "dark": {
          "value": "#0000005c",
          "type": "color"
        }
      },
      "600": {
        "light": {
          "value": "#ffffff7a",
          "type": "color"
        },
        "dark": {
          "value": "#0000007a",
          "type": "color"
        }
      },
      "700": {
        "light": {
          "value": "#ffffffa3",
          "type": "color"
        },
        "dark": {
          "value": "#000000a3",
          "type": "color"
        }
      },
      "800": {
        "light": {
          "value": "#ffffffcc",
          "type": "color"
        },
        "dark": {
          "value": "#000000cc",
          "type": "color"
        }
      },
      "900": {
        "light": {
          "value": "#ffffffeb",
          "type": "color"
        },
        "dark": {
          "value": "#000000eb",
          "type": "color"
        }
      }
    },
    "opacity-black": {
      "50": {
        "light": {
          "value": "#0000000a",
          "type": "color"
        },
        "dark": {
          "value": "#ffffff0a",
          "type": "color"
        }
      },
      "100": {
        "light": {
          "value": "#0000000f",
          "type": "color"
        },
        "dark": {
          "value": "#ffffff0f",
          "type": "color"
        }
      },
      "200": {
        "light": {
          "value": "#00000014",
          "type": "color"
        },
        "dark": {
          "value": "#ffffff14",
          "type": "color"
        }
      },
      "300": {
        "light": {
          "value": "#00000029",
          "type": "color"
        },
        "dark": {
          "value": "#ffffff29",
          "type": "color"
        }
      },
      "400": {
        "light": {
          "value": "#0000003d",
          "type": "color"
        },
        "dark": {
          "value": "#ffffff3d",
          "type": "color"
        }
      },
      "500": {
        "light": {
          "value": "#0000005c",
          "type": "color"
        },
        "dark": {
          "value": "#ffffff5c",
          "type": "color"
        }
      },
      "600": {
        "light": {
          "value": "#0000007a",
          "type": "color"
        },
        "dark": {
          "value": "#ffffff7a",
          "type": "color"
        }
      },
      "700": {
        "light": {
          "value": "#000000a3",
          "type": "color"
        },
        "dark": {
          "value": "#ffffffa3",
          "type": "color"
        }
      },
      "800": {
        "light": {
          "value": "#000000cc",
          "type": "color"
        },
        "dark": {
          "value": "#ffffffcc",
          "type": "color"
        }
      },
      "900": {
        "light": {
          "value": "#000000eb",
          "type": "color"
        },
        "dark": {
          "value": "#ffffffeb",
          "type": "color"
        }
      }
    },
    "blue": {
      "primary": {
        "value": "#3182ce",
        "type": "color"
      },
      "secondary": {
        "value": "#4299e1",
        "type": "color"
      },
      "tertiary": {
        "value": "#63b3ed",
        "type": "color"
      },
      "background": {
        "value": "#ebf8ff",
        "type": "color"
      }
    },
    "red": {
      "primary": {
        "value": "#e53e3e",
        "type": "color"
      },
      "secondary": {
        "value": "#f56565",
        "type": "color"
      },
      "tertiary": {
        "value": "#fc8181",
        "type": "color"
      },
      "background": {
        "value": "#fff5f5",
        "type": "color"
      }
    },
    "green": {
      "primary": {
        "value": "#38a169",
        "type": "color"
      },
      "secondary": {
        "value": "#48bb78",
        "type": "color"
      },
      "tertiary": {
        "value": "#68d391",
        "type": "color"
      },
      "background": {
        "value": "#f0fff4",
        "type": "color"
      }
    },
    "orange": {
      "primary": {
        "value": "#dd6b20",
        "type": "color"
      },
      "secondary": {
        "value": "#ed8936",
        "type": "color"
      },
      "tertiary": {
        "value": "#f6ad55",
        "type": "color"
      },
      "background": {
        "value": "#fffaf0",
        "type": "color"
      }
    },
    "status": {
      "primary": {
        "value": "#9f7aea",
        "type": "color"
      },
      "info": {
        "value": "#4299e1",
        "type": "color"
      },
      "success": {
        "value": "#48bb78",
        "type": "color"
      },
      "warning": {
        "value": "#ed8936",
        "type": "color"
      },
      "danger": {
        "value": "#f56565",
        "type": "color"
      }
    },
    "hover": {
      "img": {
        "value": "#0000007a",
        "type": "color"
      }
    },
    "border": {
      "primary": {
        "light": {
          "value": "#cbd5e0",
          "type": "color"
        },
        "dark": {
          "value": "#4a5568",
          "type": "color"
        }
      },
      "secondary": {
        "lightt": {
          "value": "#e2e8f0",
          "type": "color"
        },
        "dark": {
          "value": "#2d3748",
          "type": "color"
        }
      },
      "tertiary": {
        "light": {
          "value": "#edf2f7",
          "type": "color"
        },
        "dark": {
          "value": "#1a202c",
          "type": "color"
        }
      }
    },
    "text": {
      "primary": {
        "light": {
          "value": "#171923",
          "type": "color"
        },
        "dark": {
          "value": "#f7fafc",
          "type": "color"
        }
      },
      "secondary": {
        "light": {
          "value": "#718096",
          "type": "color"
        },
        "dark": {
          "value": "#cbd5e0",
          "type": "color"
        }
      },
      "tertiary": {
        "light": {
          "value": "#a0aec0",
          "type": "color"
        },
        "dark": {
          "value": "#a0aec0",
          "type": "color"
        }
      },
      "placeholder": {
        "light": {
          "value": "#a0aec0",
          "type": "color"
        },
        "dark": {
          "value": "#a0aec0",
          "type": "color"
        }
      },
      "disabled": {
        "light": {
          "value": "#cbd5e0",
          "type": "color"
        },
        "dark": {
          "value": "#718096",
          "type": "color"
        }
      },
      "white": {
        "light": {
          "value": "#f7fafc",
          "type": "color"
        },
        "dark": {
          "value": "#171923",
          "type": "color"
        }
      },
      "hoverWhite": {
        "light": {
          "value": "#f7fafc",
          "type": "color"
        },
        "dark": {
          "value": "#f7fafc",
          "type": "color"
        }
      }
    },
    "background": {
      "base": {
        "light": {
          "value": "#ffffff",
          "type": "color"
        },
        "dark": {
          "value": "#121212",
          "type": "color"
        },
        "surface": {
          "default": {
            "light": {
              "value": "#ffffff",
              "type": "color"
            },
            "dark": {
              "value": "#1a202c",
              "type": "color"
            }
          },
          "pressed": {
            "light": {
              "value": "#edf2f7",
              "type": "color"
            }
          },
          "disabled": {
            "light": {
              "value": "#ffffff",
              "type": "color"
            },
            "dark": {
              "value": "#1a202c",
              "type": "color"
            }
          }
        }
      },
      "elevated-primary": {
        "light": {
          "value": "#f7fafc",
          "type": "color"
        },
        "dark": {
          "value": "#171923",
          "type": "color"
        },
        "default": {
          "light": {
            "value": "#ffffff",
            "type": "color"
          },
          "dark": {
            "value": "#2d3748",
            "type": "color"
          }
        },
        "pressed": {
          "light": {
            "value": "#edf2f7",
            "type": "color"
          }
        },
        "disabled": {
          "light": {
            "value": "#ffffff",
            "type": "color"
          },
          "dark": {
            "value": "#2d3748",
            "type": "color"
          }
        }
      },
      "elevated-secondary": {
        "light": {
          "value": "#edf2f7",
          "type": "color"
        },
        "dark": {
          "value": "#1a202c",
          "type": "color"
        },
        "default": {
          "light": {
            "value": "#ffffff",
            "type": "color"
          },
          "dark": {
            "value": "#4a5568",
            "type": "color"
          }
        },
        "pressed": {
          "light": {
            "value": "#edf2f7",
            "type": "color"
          }
        },
        "disabled": {
          "light": {
            "value": "#ffffff",
            "type": "color"
          },
          "dark": {
            "value": "#4a5568",
            "type": "color"
          }
        }
      }
    }
  },
  "Shadows": {
    "xs": {
      "value": {
        "color": "#0000000d",
        "type": "dropShadow",
        "x": 0,
        "y": 0,
        "blur": 0,
        "spread": 1
      },
      "type": "boxShadow"
    },
    "sm": {
      "value": {
        "color": "#0000000d",
        "type": "dropShadow",
        "x": 0,
        "y": 1,
        "blur": 2,
        "spread": 0
      },
      "type": "boxShadow"
    },
    "base": {
      "value": [
        {
          "color": "#0000000f",
          "type": "dropShadow",
          "x": 0,
          "y": 1,
          "blur": 2,
          "spread": 0
        },
        {
          "color": "#0000001a",
          "type": "dropShadow",
          "x": 0,
          "y": 1,
          "blur": 3,
          "spread": 0
        }
      ],
      "type": "boxShadow"
    },
    "md": {
      "value": [
        {
          "color": "#0000000f",
          "type": "dropShadow",
          "x": 0,
          "y": 2,
          "blur": 4,
          "spread": -1
        },
        {
          "color": "#0000001a",
          "type": "dropShadow",
          "x": 0,
          "y": 4,
          "blur": 6,
          "spread": -1
        }
      ],
      "type": "boxShadow"
    },
    "lg": {
      "value": [
        {
          "color": "#0000000d",
          "type": "dropShadow",
          "x": 0,
          "y": 4,
          "blur": 6,
          "spread": -2
        },
        {
          "color": "#0000001a",
          "type": "dropShadow",
          "x": 0,
          "y": 10,
          "blur": 15,
          "spread": -3
        }
      ],
      "type": "boxShadow"
    },
    "xl": {
      "value": [
        {
          "color": "#0000000a",
          "type": "dropShadow",
          "x": 0,
          "y": 10,
          "blur": 10,
          "spread": -5
        },
        {
          "color": "#0000001a",
          "type": "dropShadow",
          "x": 0,
          "y": 20,
          "blur": 25,
          "spread": -5
        }
      ],
      "type": "boxShadow"
    },
    "2xl": {
      "value": {
        "color": "#00000040",
        "type": "dropShadow",
        "x": 0,
        "y": 25,
        "blur": 50,
        "spread": -12
      },
      "type": "boxShadow"
    },
    "outline": {
      "value": {
        "color": "#3f99e199",
        "type": "dropShadow",
        "x": 0,
        "y": 0,
        "blur": 0,
        "spread": 3
      },
      "type": "boxShadow"
    },
    "inner": {
      "value": {
        "color": "#0000000f",
        "type": "innerShadow",
        "x": 0,
        "y": 2,
        "blur": 4,
        "spread": 0
      },
      "type": "boxShadow"
    },
    "dark-lg": {
      "value": [
        {
          "color": "#00000066",
          "type": "dropShadow",
          "x": 0,
          "y": 15,
          "blur": 40,
          "spread": 0
        },
        {
          "color": "#00000033",
          "type": "dropShadow",
          "x": 0,
          "y": 5,
          "blur": 10,
          "spread": 0
        },
        {
          "color": "#0000001a",
          "type": "dropShadow",
          "x": 0,
          "y": 0,
          "blur": 0,
          "spread": 1
        }
      ],
      "type": "boxShadow"
    }
  },
  "fontFamilies": {
    "pretendard": {
      "value": "Pretendard",
      "type": "fontFamilies"
    }
  },
  "lineHeights": {
    "0": {
      "value": "130%",
      "type": "lineHeights"
    },
    "1": {
      "value": "150%",
      "type": "lineHeights"
    }
  },
  "fontWeights": {
    "pretendard-0": {
      "value": "Bold",
      "type": "fontWeights"
    },
    "pretendard-1": {
      "value": "Medium",
      "type": "fontWeights"
    },
    "pretendard-2": {
      "value": "Regular",
      "type": "fontWeights"
    }
  },
  "fontSize": {
    "0": {
      "value": 12,
      "type": "fontSizes"
    },
    "1": {
      "value": 14,
      "type": "fontSizes"
    },
    "2": {
      "value": 16,
      "type": "fontSizes"
    },
    "3": {
      "value": 18,
      "type": "fontSizes"
    },
    "4": {
      "value": 21,
      "type": "fontSizes"
    },
    "5": {
      "value": 22,
      "type": "fontSizes"
    },
    "6": {
      "value": 24,
      "type": "fontSizes"
    },
    "7": {
      "value": 28,
      "type": "fontSizes"
    },
    "8": {
      "value": 32,
      "type": "fontSizes"
    },
    "9": {
      "value": 36,
      "type": "fontSizes"
    },
    "10": {
      "value": 38,
      "type": "fontSizes"
    },
    "11": {
      "value": 50,
      "type": "fontSizes"
    }
  },
  "letterSpacing": {
    "0": {
      "value": "-4%",
      "type": "letterSpacing"
    },
    "1": {
      "value": "-2%",
      "type": "letterSpacing"
    }
  },
  "paragraphSpacing": {
    "0": {
      "value": 0,
      "type": "paragraphSpacing"
    }
  },
  "DT": {
    "hero-50": {
      "bold": {
        "value": {
          "fontFamily": "Pretendard",
          "fontWeight": "Bold",
          "lineHeight": "130%",
          "fontSize": 50,
          "letterSpacing": "-4%",
          "paragraphSpacing": 0,
          "paragraphIndent": "0px",
          "textCase": "none",
          "textDecoration": "none"
        },
        "type": "typography"
      },
      "medium": {
        "value": {
          "fontFamily": "Pretendard",
          "fontWeight": "Medium",
          "lineHeight": "130%",
          "fontSize": 50,
          "letterSpacing": "-4%",
          "paragraphSpacing": 0,
          "paragraphIndent": "0px",
          "textCase": "none",
          "textDecoration": "none"
        },
        "type": "typography"
      },
      "regular": {
        "value": {
          "fontFamily": "Pretendard",
          "fontWeight": "Regular",
          "lineHeight": "130%",
          "fontSize": 50,
          "letterSpacing": "-4%",
          "paragraphSpacing": 0,
          "paragraphIndent": "0px",
          "textCase": "none",
          "textDecoration": "none"
        },
        "type": "typography"
      }
    },
    "heading1-38": {
      "bold": {
        "value": {
          "fontFamily": "Pretendard",
          "fontWeight": "Bold",
          "lineHeight": "130%",
          "fontSize": 38,
          "letterSpacing": "-4%",
          "paragraphSpacing": 0,
          "paragraphIndent": "0px",
          "textCase": "none",
          "textDecoration": "none"
        },
        "type": "typography"
      },
      "medium": {
        "value": {
          "fontFamily": "Pretendard",
          "fontWeight": "Medium",
          "lineHeight": "130%",
          "fontSize": 38,
          "letterSpacing": "-4%",
          "paragraphSpacing": 0,
          "paragraphIndent": "0px",
          "textCase": "none",
          "textDecoration": "none"
        },
        "type": "typography"
      },
      "regular": {
        "value": {
          "fontFamily": "Pretendard",
          "fontWeight": "Regular",
          "lineHeight": "130%",
          "fontSize": 38,
          "letterSpacing": "-4%",
          "paragraphSpacing": 0,
          "paragraphIndent": "0px",
          "textCase": "none",
          "textDecoration": "none"
        },
        "type": "typography"
      }
    },
    "heading2-28": {
      "bold": {
        "value": {
          "fontFamily": "Pretendard",
          "fontWeight": "Bold",
          "lineHeight": "130%",
          "fontSize": 28,
          "letterSpacing": "-4%",
          "paragraphSpacing": 0,
          "paragraphIndent": "0px",
          "textCase": "none",
          "textDecoration": "none"
        },
        "type": "typography"
      },
      "medium": {
        "value": {
          "fontFamily": "Pretendard",
          "fontWeight": "Medium",
          "lineHeight": "130%",
          "fontSize": 28,
          "letterSpacing": "-4%",
          "paragraphSpacing": 0,
          "paragraphIndent": "0px",
          "textCase": "none",
          "textDecoration": "none"
        },
        "type": "typography"
      },
      "regular": {
        "value": {
          "fontFamily": "Pretendard",
          "fontWeight": "Regular",
          "lineHeight": "130%",
          "fontSize": 28,
          "letterSpacing": "-4%",
          "paragraphSpacing": 0,
          "paragraphIndent": "0px",
          "textCase": "none",
          "textDecoration": "none"
        },
        "type": "typography"
      }
    },
    "heading3-22": {
      "bold": {
        "value": {
          "fontFamily": "Pretendard",
          "fontWeight": "Bold",
          "lineHeight": "150%",
          "fontSize": 22,
          "letterSpacing": "-4%",
          "paragraphSpacing": 0,
          "paragraphIndent": "0px",
          "textCase": "none",
          "textDecoration": "none"
        },
        "type": "typography"
      },
      "medium": {
        "value": {
          "fontFamily": "Pretendard",
          "fontWeight": "Medium",
          "lineHeight": "150%",
          "fontSize": 22,
          "letterSpacing": "-4%",
          "paragraphSpacing": 0,
          "paragraphIndent": "0px",
          "textCase": "none",
          "textDecoration": "none"
        },
        "type": "typography"
      },
      "regular": {
        "value": {
          "fontFamily": "Pretendard",
          "fontWeight": "Regular",
          "lineHeight": "150%",
          "fontSize": 22,
          "letterSpacing": "-4%",
          "paragraphSpacing": 0,
          "paragraphIndent": "0px",
          "textCase": "none",
          "textDecoration": "none"
        },
        "type": "typography"
      }
    },
    "subHeading-18": {
      "bold": {
        "value": {
          "fontFamily": "Pretendard",
          "fontWeight": "Bold",
          "lineHeight": "150%",
          "fontSize": 18,
          "letterSpacing": "-2%",
          "paragraphSpacing": 0,
          "paragraphIndent": "0px",
          "textCase": "none",
          "textDecoration": "none"
        },
        "type": "typography"
      },
      "medium": {
        "value": {
          "fontFamily": "Pretendard",
          "fontWeight": "Medium",
          "lineHeight": "150%",
          "fontSize": 18,
          "letterSpacing": "-2%",
          "paragraphSpacing": 0,
          "paragraphIndent": "0px",
          "textCase": "none",
          "textDecoration": "none"
        },
        "type": "typography"
      },
      "regular": {
        "value": {
          "fontFamily": "Pretendard",
          "fontWeight": "Regular",
          "lineHeight": "150%",
          "fontSize": 18,
          "letterSpacing": "-2%",
          "paragraphSpacing": 0,
          "paragraphIndent": "0px",
          "textCase": "none",
          "textDecoration": "none"
        },
        "type": "typography"
      }
    },
    "body1-16": {
      "bold": {
        "value": {
          "fontFamily": "Pretendard",
          "fontWeight": "Bold",
          "lineHeight": "150%",
          "fontSize": 16,
          "letterSpacing": "-2%",
          "paragraphSpacing": 0,
          "paragraphIndent": "0px",
          "textCase": "none",
          "textDecoration": "none"
        },
        "type": "typography"
      },
      "medium": {
        "value": {
          "fontFamily": "Pretendard",
          "fontWeight": "Medium",
          "lineHeight": "150%",
          "fontSize": 16,
          "letterSpacing": "-2%",
          "paragraphSpacing": 0,
          "paragraphIndent": "0px",
          "textCase": "none",
          "textDecoration": "none"
        },
        "type": "typography"
      },
      "regular": {
        "value": {
          "fontFamily": "Pretendard",
          "fontWeight": "Regular",
          "lineHeight": "150%",
          "fontSize": 16,
          "letterSpacing": "-2%",
          "paragraphSpacing": 0,
          "paragraphIndent": "0px",
          "textCase": "none",
          "textDecoration": "none"
        },
        "type": "typography"
      }
    },
    "body2-14": {
      "bold": {
        "value": {
          "fontFamily": "Pretendard",
          "fontWeight": "Bold",
          "lineHeight": "150%",
          "fontSize": 14,
          "letterSpacing": "-2%",
          "paragraphSpacing": 0,
          "paragraphIndent": "0px",
          "textCase": "none",
          "textDecoration": "none"
        },
        "type": "typography"
      },
      "medium": {
        "value": {
          "fontFamily": "Pretendard",
          "fontWeight": "Medium",
          "lineHeight": "150%",
          "fontSize": 14,
          "letterSpacing": "-2%",
          "paragraphSpacing": 0,
          "paragraphIndent": "0px",
          "textCase": "none",
          "textDecoration": "none"
        },
        "type": "typography"
      },
      "regular": {
        "value": {
          "fontFamily": "Pretendard",
          "fontWeight": "Regular",
          "lineHeight": "150%",
          "fontSize": 14,
          "letterSpacing": "-2%",
          "paragraphSpacing": 0,
          "paragraphIndent": "0px",
          "textCase": "none",
          "textDecoration": "none"
        },
        "type": "typography"
      }
    },
    "caption-12": {
      "bold": {
        "value": {
          "fontFamily": "Pretendard",
          "fontWeight": "Bold",
          "lineHeight": "150%",
          "fontSize": 12,
          "letterSpacing": "-2%",
          "paragraphSpacing": 0,
          "paragraphIndent": "0px",
          "textCase": "none",
          "textDecoration": "none"
        },
        "type": "typography"
      },
      "medium": {
        "value": {
          "fontFamily": "Pretendard",
          "fontWeight": "Medium",
          "lineHeight": "150%",
          "fontSize": 12,
          "letterSpacing": "-2%",
          "paragraphSpacing": 0,
          "paragraphIndent": "0px",
          "textCase": "none",
          "textDecoration": "none"
        },
        "type": "typography"
      },
      "regular": {
        "value": {
          "fontFamily": "Pretendard",
          "fontWeight": "Regular",
          "lineHeight": "150%",
          "fontSize": 12,
          "letterSpacing": "-2%",
          "paragraphSpacing": 0,
          "paragraphIndent": "0px",
          "textCase": "none",
          "textDecoration": "none"
        },
        "type": "typography"
      }
    }
  },
  "MB": {
    "hero-36": {
      "bold": {
        "value": {
          "fontFamily": "Pretendard",
          "fontWeight": "Bold",
          "lineHeight": "130%",
          "fontSize": 36,
          "letterSpacing": "-4%",
          "paragraphSpacing": 0,
          "paragraphIndent": "0px",
          "textCase": "none",
          "textDecoration": "none"
        },
        "type": "typography"
      },
      "medium": {
        "value": {
          "fontFamily": "Pretendard",
          "fontWeight": "Medium",
          "lineHeight": "130%",
          "fontSize": 36,
          "letterSpacing": "-4%",
          "paragraphSpacing": 0,
          "paragraphIndent": "0px",
          "textCase": "none",
          "textDecoration": "none"
        },
        "type": "typography"
      },
      "regular": {
        "value": {
          "fontFamily": "Pretendard",
          "fontWeight": "Regular",
          "lineHeight": "130%",
          "fontSize": 36,
          "letterSpacing": "-4%",
          "paragraphSpacing": 0,
          "paragraphIndent": "0px",
          "textCase": "none",
          "textDecoration": "none"
        },
        "type": "typography"
      }
    },
    "heading1-32": {
      "bold": {
        "value": {
          "fontFamily": "Pretendard",
          "fontWeight": "Bold",
          "lineHeight": "130%",
          "fontSize": 32,
          "letterSpacing": "-4%",
          "paragraphSpacing": 0,
          "paragraphIndent": "0px",
          "textCase": "none",
          "textDecoration": "none"
        },
        "type": "typography"
      },
      "medium": {
        "value": {
          "fontFamily": "Pretendard",
          "fontWeight": "Medium",
          "lineHeight": "130%",
          "fontSize": 32,
          "letterSpacing": "-4%",
          "paragraphSpacing": 0,
          "paragraphIndent": "0px",
          "textCase": "none",
          "textDecoration": "none"
        },
        "type": "typography"
      },
      "regular": {
        "value": {
          "fontFamily": "Pretendard",
          "fontWeight": "Regular",
          "lineHeight": "130%",
          "fontSize": 32,
          "letterSpacing": "-4%",
          "paragraphSpacing": 0,
          "paragraphIndent": "0px",
          "textCase": "none",
          "textDecoration": "none"
        },
        "type": "typography"
      }
    },
    "heading2-24": {
      "bold": {
        "value": {
          "fontFamily": "Pretendard",
          "fontWeight": "Bold",
          "lineHeight": "130%",
          "fontSize": 24,
          "letterSpacing": "-4%",
          "paragraphSpacing": 0,
          "paragraphIndent": "0px",
          "textCase": "none",
          "textDecoration": "none"
        },
        "type": "typography"
      },
      "medium": {
        "value": {
          "fontFamily": "Pretendard",
          "fontWeight": "Medium",
          "lineHeight": "130%",
          "fontSize": 24,
          "letterSpacing": "-4%",
          "paragraphSpacing": 0,
          "paragraphIndent": "0px",
          "textCase": "none",
          "textDecoration": "none"
        },
        "type": "typography"
      },
      "regular": {
        "value": {
          "fontFamily": "Pretendard",
          "fontWeight": "Regular",
          "lineHeight": "130%",
          "fontSize": 24,
          "letterSpacing": "-4%",
          "paragraphSpacing": 0,
          "paragraphIndent": "0px",
          "textCase": "none",
          "textDecoration": "none"
        },
        "type": "typography"
      }
    },
    "heading3-21": {
      "bold": {
        "value": {
          "fontFamily": "Pretendard",
          "fontWeight": "Bold",
          "lineHeight": "150%",
          "fontSize": 21,
          "letterSpacing": "-4%",
          "paragraphSpacing": 0,
          "paragraphIndent": "0px",
          "textCase": "none",
          "textDecoration": "none"
        },
        "type": "typography"
      },
      "medium": {
        "value": {
          "fontFamily": "Pretendard",
          "fontWeight": "Medium",
          "lineHeight": "150%",
          "fontSize": 21,
          "letterSpacing": "-4%",
          "paragraphSpacing": 0,
          "paragraphIndent": "0px",
          "textCase": "none",
          "textDecoration": "none"
        },
        "type": "typography"
      },
      "regular": {
        "value": {
          "fontFamily": "Pretendard",
          "fontWeight": "Regular",
          "lineHeight": "150%",
          "fontSize": 21,
          "letterSpacing": "-4%",
          "paragraphSpacing": 0,
          "paragraphIndent": "0px",
          "textCase": "none",
          "textDecoration": "none"
        },
        "type": "typography"
      }
    },
    "subHeading-18": {
      "bold": {
        "value": {
          "fontFamily": "Pretendard",
          "fontWeight": "Bold",
          "lineHeight": "150%",
          "fontSize": 18,
          "letterSpacing": "-2%",
          "paragraphSpacing": 0,
          "paragraphIndent": "0px",
          "textCase": "none",
          "textDecoration": "none"
        },
        "type": "typography"
      },
      "medium": {
        "value": {
          "fontFamily": "Pretendard",
          "fontWeight": "Medium",
          "lineHeight": "150%",
          "fontSize": 18,
          "letterSpacing": "-2%",
          "paragraphSpacing": 0,
          "paragraphIndent": "0px",
          "textCase": "none",
          "textDecoration": "none"
        },
        "type": "typography"
      },
      "regular": {
        "value": {
          "fontFamily": "Pretendard",
          "fontWeight": "Regular",
          "lineHeight": "150%",
          "fontSize": 18,
          "letterSpacing": "-2%",
          "paragraphSpacing": 0,
          "paragraphIndent": "0px",
          "textCase": "none",
          "textDecoration": "none"
        },
        "type": "typography"
      }
    },
    "body1-16": {
      "bold": {
        "value": {
          "fontFamily": "Pretendard",
          "fontWeight": "Bold",
          "lineHeight": "150%",
          "fontSize": 16,
          "letterSpacing": "-2%",
          "paragraphSpacing": 0,
          "paragraphIndent": "0px",
          "textCase": "none",
          "textDecoration": "none"
        },
        "type": "typography"
      },
      "medium": {
        "value": {
          "fontFamily": "Pretendard",
          "fontWeight": "Medium",
          "lineHeight": "150%",
          "fontSize": 16,
          "letterSpacing": "-2%",
          "paragraphSpacing": 0,
          "paragraphIndent": "0px",
          "textCase": "none",
          "textDecoration": "none"
        },
        "type": "typography"
      },
      "regular": {
        "value": {
          "fontFamily": "Pretendard",
          "fontWeight": "Regular",
          "lineHeight": "150%",
          "fontSize": 16,
          "letterSpacing": "-2%",
          "paragraphSpacing": 0,
          "paragraphIndent": "0px",
          "textCase": "none",
          "textDecoration": "none"
        },
        "type": "typography"
      }
    },
    "body2-14": {
      "bold": {
        "value": {
          "fontFamily": "Pretendard",
          "fontWeight": "Bold",
          "lineHeight": "150%",
          "fontSize": 14,
          "letterSpacing": "-2%",
          "paragraphSpacing": 0,
          "paragraphIndent": "0px",
          "textCase": "none",
          "textDecoration": "none"
        },
        "type": "typography"
      },
      "medium": {
        "value": {
          "fontFamily": "Pretendard",
          "fontWeight": "Medium",
          "lineHeight": "150%",
          "fontSize": 14,
          "letterSpacing": "-2%",
          "paragraphSpacing": 0,
          "paragraphIndent": "0px",
          "textCase": "none",
          "textDecoration": "none"
        },
        "type": "typography"
      },
      "regular": {
        "value": {
          "fontFamily": "Pretendard",
          "fontWeight": "Regular",
          "lineHeight": "150%",
          "fontSize": 14,
          "letterSpacing": "-2%",
          "paragraphSpacing": 0,
          "paragraphIndent": "0px",
          "textCase": "none",
          "textDecoration": "none"
        },
        "type": "typography"
      }
    },
    "caption-12": {
      "bold": {
        "value": {
          "fontFamily": "Pretendard",
          "fontWeight": "Bold",
          "lineHeight": "150%",
          "fontSize": 12,
          "letterSpacing": "-2%",
          "paragraphSpacing": 0,
          "paragraphIndent": "0px",
          "textCase": "none",
          "textDecoration": "none"
        },
        "type": "typography"
      },
      "medium": {
        "value": {
          "fontFamily": "Pretendard",
          "fontWeight": "Medium",
          "lineHeight": "150%",
          "fontSize": 12,
          "letterSpacing": "-2%",
          "paragraphSpacing": 0,
          "paragraphIndent": "0px",
          "textCase": "none",
          "textDecoration": "none"
        },
        "type": "typography"
      },
      "regular": {
        "value": {
          "fontFamily": "Pretendard",
          "fontWeight": "Regular",
          "lineHeight": "150%",
          "fontSize": 12,
          "letterSpacing": "-2%",
          "paragraphSpacing": 0,
          "paragraphIndent": "0px",
          "textCase": "none",
          "textDecoration": "none"
        },
        "type": "typography"
      }
    }
  },
  "textCase": {
    "none": {
      "value": "none",
      "type": "textCase"
    }
  },
  "textDecoration": {
    "none": {
      "value": "none",
      "type": "textDecoration"
    }
  },
  "paragraphIndent": {
    "0": {
      "value": "0px",
      "type": "dimension"
    }
  }
}